{
	"count": 20,
	"start": 0,
	"total": 30,
	"subjects": [
		{
			"rating": {
				"max": 10,
				"average": 9.0,
				"stars": "45",
				"min": 0
			},
			"genres": [
				"剧情",
				"喜剧"
			],
			"title": "我不是药神",
			"casts": [
				{
					"alt": "https:\/\/movie.douban.com\/celebrity\/1274297\/",
					"avatars": {
						"small": "https://img1.doubanio.com\/view\/celebrity\/s_ratio_celebrity\/public\/p43738.jpg",
						"large": "https://img1.doubanio.com\/view\/celebrity\/s_ratio_celebrity\/public\/p43738.jpg",
						"medium": "https://img1.doubanio.com\/view\/celebrity\/s_ratio_celebrity\/public\/p43738.jpg"
					},
					"name": "徐峥",
					"id": "1274297"
				},
				{
					"alt": "https:\/\/movie.douban.com\/celebrity\/1313837\/",
					"avatars": {
						"small": "https://img1.doubanio.com\/view\/celebrity\/s_ratio_celebrity\/public\/p1496577458.38.jpg",
						"large": "https://img1.doubanio.com\/view\/celebrity\/s_ratio_celebrity\/public\/p1496577458.38.jpg",
						"medium": "https://img1.doubanio.com\/view\/celebrity\/s_ratio_celebrity\/public\/p1496577458.38.jpg"
					},
					"name": "王传君",
					"id": "1313837"
				},
				{
					"alt": "https:\/\/movie.douban.com\/celebrity\/1276085\/",
					"avatars": {
						"small": "https://img3.doubanio.com\/view\/celebrity\/s_ratio_celebrity\/public\/p1514533436.1.jpg",
						"large": "https://img3.doubanio.com\/view\/celebrity\/s_ratio_celebrity\/public\/p1514533436.1.jpg",
						"medium": "https://img3.doubanio.com\/view\/celebrity\/s_ratio_celebrity\/public\/p1514533436.1.jpg"
					},
					"name": "周一围",
					"id": "1276085"
				}
			],
			"collect_count": 157155,
			"original_title": "我不是药神",
			"subtype": "movie",
			"directors": [
				{
					"alt": "https:\/\/movie.douban.com\/celebrity\/1349765\/",
					"avatars": {
						"small": "https://img3.doubanio.com\/view\/celebrity\/s_ratio_celebrity\/public\/p1529658740.26.jpg",
						"large": "https://img3.doubanio.com\/view\/celebrity\/s_ratio_celebrity\/public\/p1529658740.26.jpg",
						"medium": "https://img3.doubanio.com\/view\/celebrity\/s_ratio_celebrity\/public\/p1529658740.26.jpg"
					},
					"name": "文牧野",
					"id": "1349765"
				}
			],
			"year": "2018",
			"images": {
				"small": "https://img3.doubanio.com\/view\/photo\/s_ratio_poster\/public\/p2519070834.jpg",
				"large": "https://img3.doubanio.com\/view\/photo\/s_ratio_poster\/public\/p2519070834.jpg",
				"medium": "https://img3.doubanio.com\/view\/photo\/s_ratio_poster\/public\/p2519070834.jpg"
			},
			"alt": "https:\/\/movie.douban.com\/subject\/26752088\/",
			"id": "26752088"
		},
		{
			"rating": {
				"max": 10,
				"average": 0,
				"stars": "00",
				"min": 0
			},
			"genres": [
				"儿童",
				"动画",
				"冒险"
			],
			"title": "新大头儿子和小头爸爸3：俄罗斯奇遇记",
			"casts": [
				{
					"alt": "https:\/\/movie.douban.com\/celebrity\/1318433\/",
					"avatars": {
						"small": "https://img1.doubanio.com\/view\/celebrity\/s_ratio_celebrity\/public\/p44177.jpg",
						"large": "https://img1.doubanio.com\/view\/celebrity\/s_ratio_celebrity\/public\/p44177.jpg",
						"medium": "https://img1.doubanio.com\/view\/celebrity\/s_ratio_celebrity\/public\/p44177.jpg"
					},
					"name": "刘纯燕",
					"id": "1318433"
				},
				{
					"alt": "https:\/\/movie.douban.com\/celebrity\/1318435\/",
					"avatars": {
						"small": "https://img3.doubanio.com\/view\/celebrity\/s_ratio_celebrity\/public\/p44180.jpg",
						"large": "https://img3.doubanio.com\/view\/celebrity\/s_ratio_celebrity\/public\/p44180.jpg",
						"medium": "https://img3.doubanio.com\/view\/celebrity\/s_ratio_celebrity\/public\/p44180.jpg"
					},
					"name": "董浩",
					"id": "1318435"
				},
				{
					"alt": "https:\/\/movie.douban.com\/celebrity\/1274251\/",
					"avatars": {
						"small": "https://img3.doubanio.com\/view\/celebrity\/s_ratio_celebrity\/public\/p1494778054.15.jpg",
						"large": "https://img3.doubanio.com\/view\/celebrity\/s_ratio_celebrity\/public\/p1494778054.15.jpg",
						"medium": "https://img3.doubanio.com\/view\/celebrity\/s_ratio_celebrity\/public\/p1494778054.15.jpg"
					},
					"name": "鞠萍",
					"id": "1274251"
				}
			],
			"collect_count": 79,
			"original_title": "新大头儿子和小头爸爸3：俄罗斯奇遇记",
			"subtype": "movie",
			"directors": [
				{
					"alt": "https:\/\/movie.douban.com\/celebrity\/1342907\/",
					"avatars": {
						"small": "https://img1.doubanio.com\/view\/celebrity\/s_ratio_celebrity\/public\/p1469705072.9.jpg",
						"large": "https://img1.doubanio.com\/view\/celebrity\/s_ratio_celebrity\/public\/p1469705072.9.jpg",
						"medium": "https://img1.doubanio.com\/view\/celebrity\/s_ratio_celebrity\/public\/p1469705072.9.jpg"
					},
					"name": "何澄",
					"id": "1342907"
				}
			],
			"year": "2018",
			"images": {
				"small": "https://img3.doubanio.com\/view\/photo\/s_ratio_poster\/public\/p2522820714.jpg",
				"large": "https://img3.doubanio.com\/view\/photo\/s_ratio_poster\/public\/p2522820714.jpg",
				"medium": "https://img3.doubanio.com\/view\/photo\/s_ratio_poster\/public\/p2522820714.jpg"
			},
			"alt": "https:\/\/movie.douban.com\/subject\/30198729\/",
			"id": "30198729"
		},
		{
			"rating": {
				"max": 10,
				"average": 7.4,
				"stars": "40",
				"min": 0
			},
			"genres": [
				"剧情",
				"动作",
				"冒险"
			],
			"title": "动物世界",
			"casts": [
				{
					"alt": "https:\/\/movie.douban.com\/celebrity\/1314140\/",
					"avatars": {
						"small": "https://img1.doubanio.com\/view\/celebrity\/s_ratio_celebrity\/public\/p1403196522.98.jpg",
						"large": "https://img1.doubanio.com\/view\/celebrity\/s_ratio_celebrity\/public\/p1403196522.98.jpg",
						"medium": "https://img1.doubanio.com\/view\/celebrity\/s_ratio_celebrity\/public\/p1403196522.98.jpg"
					},
					"name": "李易峰",
					"id": "1314140"
				},
				{
					"alt": "https:\/\/movie.douban.com\/celebrity\/1053620\/",
					"avatars": {
						"small": "https://img3.doubanio.com\/view\/celebrity\/s_ratio_celebrity\/public\/p4023.jpg",
						"large": "https://img3.doubanio.com\/view\/celebrity\/s_ratio_celebrity\/public\/p4023.jpg",
						"medium": "https://img3.doubanio.com\/view\/celebrity\/s_ratio_celebrity\/public\/p4023.jpg"
					},
					"name": "迈克尔·道格拉斯",
					"id": "1053620"
				},
				{
					"alt": "https:\/\/movie.douban.com\/celebrity\/1274224\/",
					"avatars": {
						"small": "https://img1.doubanio.com\/view\/celebrity\/s_ratio_celebrity\/public\/p36798.jpg",
						"large": "https://img1.doubanio.com\/view\/celebrity\/s_ratio_celebrity\/public\/p36798.jpg",
						"medium": "https://img1.doubanio.com\/view\/celebrity\/s_ratio_celebrity\/public\/p36798.jpg"
					},
					"name": "周冬雨",
					"id": "1274224"
				}
			],
			"collect_count": 93917,
			"original_title": "动物世界",
			"subtype": "movie",
			"directors": [
				{
					"alt": "https:\/\/movie.douban.com\/celebrity\/1314828\/",
					"avatars": {
						"small": "https://img3.doubanio.com\/view\/celebrity\/s_ratio_celebrity\/public\/p38015.jpg",
						"large": "https://img3.doubanio.com\/view\/celebrity\/s_ratio_celebrity\/public\/p38015.jpg",
						"medium": "https://img3.doubanio.com\/view\/celebrity\/s_ratio_celebrity\/public\/p38015.jpg"
					},
					"name": "韩延",
					"id": "1314828"
				}
			],
			"year": "2018",
			"images": {
				"small": "https://img1.doubanio.com\/view\/photo\/s_ratio_poster\/public\/p2525528688.jpg",
				"large": "https://img1.doubanio.com\/view\/photo\/s_ratio_poster\/public\/p2525528688.jpg",
				"medium": "https://img1.doubanio.com\/view\/photo\/s_ratio_poster\/public\/p2525528688.jpg"
			},
			"alt": "https:\/\/movie.douban.com\/subject\/26925317\/",
			"id": "26925317"
		},
		{
			"rating": {
				"max": 10,
				"average": 6.9,
				"stars": "35",
				"min": 0
			},
			"genres": [
				"动作",
				"科幻",
				"冒险"
			],
			"title": "侏罗纪世界2",
			"casts": [
				{
					"alt": "https:\/\/movie.douban.com\/celebrity\/1017967\/",
					"avatars": {
						"small": "https://img3.doubanio.com\/view\/celebrity\/s_ratio_celebrity\/public\/p1408711300.32.jpg",
						"large": "https://img3.doubanio.com\/view\/celebrity\/s_ratio_celebrity\/public\/p1408711300.32.jpg",
						"medium": "https://img3.doubanio.com\/view\/celebrity\/s_ratio_celebrity\/public\/p1408711300.32.jpg"
					},
					"name": "克里斯·帕拉特",
					"id": "1017967"
				},
				{
					"alt": "https:\/\/movie.douban.com\/celebrity\/1027772\/",
					"avatars": {
						"small": "https://img3.doubanio.com\/view\/celebrity\/s_ratio_celebrity\/public\/p315.jpg",
						"large": "https://img3.doubanio.com\/view\/celebrity\/s_ratio_celebrity\/public\/p315.jpg",
						"medium": "https://img3.doubanio.com\/view\/celebrity\/s_ratio_celebrity\/public\/p315.jpg"
					},
					"name": "布莱丝·达拉斯·霍华德",
					"id": "1027772"
				},
				{
					"alt": "https:\/\/movie.douban.com\/celebrity\/1350981\/",
					"avatars": {
						"small": "https://img3.doubanio.com\/view\/celebrity\/s_ratio_celebrity\/public\/p1523860646.23.jpg",
						"large": "https://img3.doubanio.com\/view\/celebrity\/s_ratio_celebrity\/public\/p1523860646.23.jpg",
						"medium": "https://img3.doubanio.com\/view\/celebrity\/s_ratio_celebrity\/public\/p1523860646.23.jpg"
					},
					"name": "贾斯蒂斯·史密斯",
					"id": "1350981"
				}
			],
			"collect_count": 147382,
			"original_title": "Jurassic World: Fallen Kingdom",
			"subtype": "movie",
			"directors": [
				{
					"alt": "https:\/\/movie.douban.com\/celebrity\/1305510\/",
					"avatars": {
						"small": "https://img3.doubanio.com\/view\/celebrity\/s_ratio_celebrity\/public\/p1372318484.25.jpg",
						"large": "https://img3.doubanio.com\/view\/celebrity\/s_ratio_celebrity\/public\/p1372318484.25.jpg",
						"medium": "https://img3.doubanio.com\/view\/celebrity\/s_ratio_celebrity\/public\/p1372318484.25.jpg"
					},
					"name": "胡安·安东尼奥·巴亚纳",
					"id": "1305510"
				}
			],
			"year": "2018",
			"images": {
				"small": "https://img3.doubanio.com\/view\/photo\/s_ratio_poster\/public\/p2522069454.jpg",
				"large": "https://img3.doubanio.com\/view\/photo\/s_ratio_poster\/public\/p2522069454.jpg",
				"medium": "https://img3.doubanio.com\/view\/photo\/s_ratio_poster\/public\/p2522069454.jpg"
			},
			"alt": "https:\/\/movie.douban.com\/subject\/26416062\/",
			"id": "26416062"
		},
		{
			"rating": {
				"max": 10,
				"average": 8.1,
				"stars": "40",
				"min": 0
			},
			"genres": [
				"喜剧",
				"动作",
				"动画"
			],
			"title": "超人总动员2",
			"casts": [
				{
					"alt": "https:\/\/movie.douban.com\/celebrity\/1002721\/",
					"avatars": {
						"small": "https://img1.doubanio.com\/view\/celebrity\/s_ratio_celebrity\/public\/p21297.jpg",
						"large": "https://img1.doubanio.com\/view\/celebrity\/s_ratio_celebrity\/public\/p21297.jpg",
						"medium": "https://img1.doubanio.com\/view\/celebrity\/s_ratio_celebrity\/public\/p21297.jpg"
					},
					"name": "格雷格·T·尼尔森",
					"id": "1002721"
				},
				{
					"alt": "https:\/\/movie.douban.com\/celebrity\/1031838\/",
					"avatars": {
						"small": "https://img3.doubanio.com\/view\/celebrity\/s_ratio_celebrity\/public\/p48614.jpg",
						"large": "https://img3.doubanio.com\/view\/celebrity\/s_ratio_celebrity\/public\/p48614.jpg",
						"medium": "https://img3.doubanio.com\/view\/celebrity\/s_ratio_celebrity\/public\/p48614.jpg"
					},
					"name": "霍利·亨特",
					"id": "1031838"
				},
				{
					"alt": "https:\/\/movie.douban.com\/celebrity\/1186797\/",
					"avatars": {
						"small": "https://img3.doubanio.com\/view\/celebrity\/s_ratio_celebrity\/public\/p1529654136.33.jpg",
						"large": "https://img3.doubanio.com\/view\/celebrity\/s_ratio_celebrity\/public\/p1529654136.33.jpg",
						"medium": "https://img3.doubanio.com\/view\/celebrity\/s_ratio_celebrity\/public\/p1529654136.33.jpg"
					},
					"name": "莎拉·沃威尔",
					"id": "1186797"
				}
			],
			"collect_count": 68054,
			"original_title": "Incredibles 2",
			"subtype": "movie",
			"directors": [
				{
					"alt": "https:\/\/movie.douban.com\/celebrity\/1027204\/",
					"avatars": {
						"small": "https://img3.doubanio.com\/view\/celebrity\/s_ratio_celebrity\/public\/p1529655910.45.jpg",
						"large": "https://img3.doubanio.com\/view\/celebrity\/s_ratio_celebrity\/public\/p1529655910.45.jpg",
						"medium": "https://img3.doubanio.com\/view\/celebrity\/s_ratio_celebrity\/public\/p1529655910.45.jpg"
					},
					"name": "布拉德·伯德",
					"id": "1027204"
				}
			],
			"year": "2018",
			"images": {
				"small": "https://img3.doubanio.com\/view\/photo\/s_ratio_poster\/public\/p2522880251.jpg",
				"large": "https://img3.doubanio.com\/view\/photo\/s_ratio_poster\/public\/p2522880251.jpg",
				"medium": "https://img3.doubanio.com\/view\/photo\/s_ratio_poster\/public\/p2522880251.jpg"
			},
			"alt": "https:\/\/movie.douban.com\/subject\/25849049\/",
			"id": "25849049"
		},
		{
			"rating": {
				"max": 10,
				"average": 3.2,
				"stars": "15",
				"min": 0
			},
			"genres": [
				"动作",
				"惊悚"
			],
			"title": "金蝉脱壳2：冥府",
			"casts": [
				{
					"alt": "https:\/\/movie.douban.com\/celebrity\/1047996\/",
					"avatars": {
						"small": "https://img3.doubanio.com\/view\/celebrity\/s_ratio_celebrity\/public\/p262.jpg",
						"large": "https://img3.doubanio.com\/view\/celebrity\/s_ratio_celebrity\/public\/p262.jpg",
						"medium": "https://img3.doubanio.com\/view\/celebrity\/s_ratio_celebrity\/public\/p262.jpg"
					},
					"name": "西尔维斯特·史泰龙",
					"id": "1047996"
				},
				{
					"alt": "https:\/\/movie.douban.com\/celebrity\/1041404\/",
					"avatars": {
						"small": "https://img3.doubanio.com\/view\/celebrity\/s_ratio_celebrity\/public\/p1472787652.32.jpg",
						"large": "https://img3.doubanio.com\/view\/celebrity\/s_ratio_celebrity\/public\/p1472787652.32.jpg",
						"medium": "https://img3.doubanio.com\/view\/celebrity\/s_ratio_celebrity\/public\/p1472787652.32.jpg"
					},
					"name": "黄晓明",
					"id": "1041404"
				},
				{
					"alt": "https:\/\/movie.douban.com\/celebrity\/1014003\/",
					"avatars": {
						"small": "https://img3.doubanio.com\/view\/celebrity\/s_ratio_celebrity\/public\/p1493202154.34.jpg",
						"large": "https://img3.doubanio.com\/view\/celebrity\/s_ratio_celebrity\/public\/p1493202154.34.jpg",
						"medium": "https://img3.doubanio.com\/view\/celebrity\/s_ratio_celebrity\/public\/p1493202154.34.jpg"
					},
					"name": "戴夫·巴蒂斯塔",
					"id": "1014003"
				}
			],
			"collect_count": 16677,
			"original_title": "Escape Plan 2: Hades",
			"subtype": "movie",
			"directors": [
				{
					"alt": "https:\/\/movie.douban.com\/celebrity\/1032824\/",
					"avatars": {
						"small": "https://img3.doubanio.com\/view\/celebrity\/s_ratio_celebrity\/public\/p1473210941.06.jpg",
						"large": "https://img3.doubanio.com\/view\/celebrity\/s_ratio_celebrity\/public\/p1473210941.06.jpg",
						"medium": "https://img3.doubanio.com\/view\/celebrity\/s_ratio_celebrity\/public\/p1473210941.06.jpg"
					},
					"name": "史蒂芬·C·米勒",
					"id": "1032824"
				}
			],
			"year": "2018",
			"images": {
				"small": "https://img3.doubanio.com\/view\/photo\/s_ratio_poster\/public\/p2524134770.jpg",
				"large": "https://img3.doubanio.com\/view\/photo\/s_ratio_poster\/public\/p2524134770.jpg",
				"medium": "https://img3.doubanio.com\/view\/photo\/s_ratio_poster\/public\/p2524134770.jpg"
			},
			"alt": "https:\/\/movie.douban.com\/subject\/26905469\/",
			"id": "26905469"
		},
		{
			"rating": {
				"max": 10,
				"average": 0,
				"stars": "00",
				"min": 0
			},
			"genres": [
				"纪录片"
			],
			"title": "您一定不要错过",
			"casts": [
				{
					"alt": "https:\/\/movie.douban.com\/celebrity\/1315258\/",
					"avatars": {
						"small": "https://img1.doubanio.com\/view\/celebrity\/s_ratio_celebrity\/public\/p1524126104.69.jpg",
						"large": "https://img1.doubanio.com\/view\/celebrity\/s_ratio_celebrity\/public\/p1524126104.69.jpg",
						"medium": "https://img1.doubanio.com\/view\/celebrity\/s_ratio_celebrity\/public\/p1524126104.69.jpg"
					},
					"name": "崔永元",
					"id": "1315258"
				},
				{
					"alt": "https:\/\/movie.douban.com\/celebrity\/1163063\/",
					"avatars": {
						"small": "https://img1.doubanio.com\/view\/celebrity\/s_ratio_celebrity\/public\/p33449.jpg",
						"large": "https://img1.doubanio.com\/view\/celebrity\/s_ratio_celebrity\/public\/p33449.jpg",
						"medium": "https://img1.doubanio.com\/view\/celebrity\/s_ratio_celebrity\/public\/p33449.jpg"
					},
					"name": "王心刚",
					"id": "1163063"
				},
				{
					"alt": "https:\/\/movie.douban.com\/celebrity\/1017754\/",
					"avatars": {
						"small": "https://img1.doubanio.com\/view\/celebrity\/s_ratio_celebrity\/public\/p20607.jpg",
						"large": "https://img1.doubanio.com\/view\/celebrity\/s_ratio_celebrity\/public\/p20607.jpg",
						"medium": "https://img1.doubanio.com\/view\/celebrity\/s_ratio_celebrity\/public\/p20607.jpg"
					},
					"name": "王晓棠",
					"id": "1017754"
				}
			],
			"collect_count": 64,
			"original_title": "您一定不要错过",
			"subtype": "movie",
			"directors": [
				{
					"alt": "https:\/\/movie.douban.com\/celebrity\/1290135\/",
					"avatars": {
						"small": "https://img3.doubanio.com\/view\/celebrity\/s_ratio_celebrity\/public\/p1372142956.93.jpg",
						"large": "https://img3.doubanio.com\/view\/celebrity\/s_ratio_celebrity\/public\/p1372142956.93.jpg",
						"medium": "https://img3.doubanio.com\/view\/celebrity\/s_ratio_celebrity\/public\/p1372142956.93.jpg"
					},
					"name": "麦丽丝",
					"id": "1290135"
				}
			],
			"year": "2018",
			"images": {
				"small": "https://img3.doubanio.com\/view\/photo\/s_ratio_poster\/public\/p2525923740.jpg",
				"large": "https://img3.doubanio.com\/view\/photo\/s_ratio_poster\/public\/p2525923740.jpg",
				"medium": "https://img3.doubanio.com\/view\/photo\/s_ratio_poster\/public\/p2525923740.jpg"
			},
			"alt": "https:\/\/movie.douban.com\/subject\/30255216\/",
			"id": "30255216"
		},
		{
			"rating": {
				"max": 10,
				"average": 8.5,
				"stars": "45",
				"min": 0
			},
			"genres": [
				"犯罪",
				"剧情",
				"爱情"
			],
			"title": "阿飞正传",
			"casts": [
				{
					"alt": "https:\/\/movie.douban.com\/celebrity\/1003494\/",
					"avatars": {
						"small": "https://img1.doubanio.com\/view\/celebrity\/s_ratio_celebrity\/public\/p67.jpg",
						"large": "https://img1.doubanio.com\/view\/celebrity\/s_ratio_celebrity\/public\/p67.jpg",
						"medium": "https://img1.doubanio.com\/view\/celebrity\/s_ratio_celebrity\/public\/p67.jpg"
					},
					"name": "张国荣",
					"id": "1003494"
				},
				{
					"alt": "https:\/\/movie.douban.com\/celebrity\/1274231\/",
					"avatars": {
						"small": "https://img3.doubanio.com\/view\/celebrity\/s_ratio_celebrity\/public\/p793.jpg",
						"large": "https://img3.doubanio.com\/view\/celebrity\/s_ratio_celebrity\/public\/p793.jpg",
						"medium": "https://img3.doubanio.com\/view\/celebrity\/s_ratio_celebrity\/public\/p793.jpg"
					},
					"name": "张曼玉",
					"id": "1274231"
				},
				{
					"alt": "https:\/\/movie.douban.com\/celebrity\/1036905\/",
					"avatars": {
						"small": "https://img1.doubanio.com\/view\/celebrity\/s_ratio_celebrity\/public\/p1411832447.57.jpg",
						"large": "https://img1.doubanio.com\/view\/celebrity\/s_ratio_celebrity\/public\/p1411832447.57.jpg",
						"medium": "https://img1.doubanio.com\/view\/celebrity\/s_ratio_celebrity\/public\/p1411832447.57.jpg"
					},
					"name": "刘嘉玲",
					"id": "1036905"
				}
			],
			"collect_count": 284282,
			"original_title": "阿飛正傳",
			"subtype": "movie",
			"directors": [
				{
					"alt": "https:\/\/movie.douban.com\/celebrity\/1041024\/",
					"avatars": {
						"small": "https://img1.doubanio.com\/view\/celebrity\/s_ratio_celebrity\/public\/p1418226223.7.jpg",
						"large": "https://img1.doubanio.com\/view\/celebrity\/s_ratio_celebrity\/public\/p1418226223.7.jpg",
						"medium": "https://img1.doubanio.com\/view\/celebrity\/s_ratio_celebrity\/public\/p1418226223.7.jpg"
					},
					"name": "王家卫",
					"id": "1041024"
				}
			],
			"year": "1990",
			"images": {
				"small": "https://img3.doubanio.com\/view\/photo\/s_ratio_poster\/public\/p2525770523.jpg",
				"large": "https://img3.doubanio.com\/view\/photo\/s_ratio_poster\/public\/p2525770523.jpg",
				"medium": "https://img3.doubanio.com\/view\/photo\/s_ratio_poster\/public\/p2525770523.jpg"
			},
			"alt": "https:\/\/movie.douban.com\/subject\/1305690\/",
			"id": "1305690"
		},
		{
			"rating": {
				"max": 10,
				"average": 3.7,
				"stars": "20",
				"min": 0
			},
			"genres": [
				"喜剧",
				"动作"
			],
			"title": "猛虫过江",
			"casts": [
				{
					"alt": "https:\/\/movie.douban.com\/celebrity\/1274081\/",
					"avatars": {
						"small": "https://img3.doubanio.com\/view\/celebrity\/s_ratio_celebrity\/public\/p34055.jpg",
						"large": "https://img3.doubanio.com\/view\/celebrity\/s_ratio_celebrity\/public\/p34055.jpg",
						"medium": "https://img3.doubanio.com\/view\/celebrity\/s_ratio_celebrity\/public\/p34055.jpg"
					},
					"name": "小沈阳",
					"id": "1274081"
				},
				{
					"alt": "https:\/\/movie.douban.com\/celebrity\/1316365\/",
					"avatars": {
						"small": "https://img3.doubanio.com\/view\/celebrity\/s_ratio_celebrity\/public\/p36063.jpg",
						"large": "https://img3.doubanio.com\/view\/celebrity\/s_ratio_celebrity\/public\/p36063.jpg",
						"medium": "https://img3.doubanio.com\/view\/celebrity\/s_ratio_celebrity\/public\/p36063.jpg"
					},
					"name": "潘斌龙",
					"id": "1316365"
				},
				{
					"alt": "https:\/\/movie.douban.com\/celebrity\/1341903\/",
					"avatars": {
						"small": "https://img1.doubanio.com\/view\/celebrity\/s_ratio_celebrity\/public\/p1446281965.79.jpg",
						"large": "https://img1.doubanio.com\/view\/celebrity\/s_ratio_celebrity\/public\/p1446281965.79.jpg",
						"medium": "https://img1.doubanio.com\/view\/celebrity\/s_ratio_celebrity\/public\/p1446281965.79.jpg"
					},
					"name": "宋芸桦",
					"id": "1341903"
				}
			],
			"collect_count": 9770,
			"original_title": "猛虫过江",
			"subtype": "movie",
			"directors": [
				{
					"alt": "https:\/\/movie.douban.com\/celebrity\/1274081\/",
					"avatars": {
						"small": "https://img3.doubanio.com\/view\/celebrity\/s_ratio_celebrity\/public\/p34055.jpg",
						"large": "https://img3.doubanio.com\/view\/celebrity\/s_ratio_celebrity\/public\/p34055.jpg",
						"medium": "https://img3.doubanio.com\/view\/celebrity\/s_ratio_celebrity\/public\/p34055.jpg"
					},
					"name": "小沈阳",
					"id": "1274081"
				}
			],
			"year": "2018",
			"images": {
				"small": "https://img1.doubanio.com\/view\/photo\/s_ratio_poster\/public\/p2523437699.jpg",
				"large": "https://img1.doubanio.com\/view\/photo\/s_ratio_poster\/public\/p2523437699.jpg",
				"medium": "https://img1.doubanio.com\/view\/photo\/s_ratio_poster\/public\/p2523437699.jpg"
			},
			"alt": "https:\/\/movie.douban.com\/subject\/26818314\/",
			"id": "26818314"
		},
		{
			"rating": {
				"max": 10,
				"average": 0,
				"stars": "00",
				"min": 0
			},
			"genres": [
				"惊悚",
				"恐怖"
			],
			"title": "细思极恐",
			"casts": [
				{
					"alt": "https:\/\/movie.douban.com\/celebrity\/1178533\/",
					"avatars": {
						"small": "https://img3.doubanio.com\/view\/celebrity\/s_ratio_celebrity\/public\/p21430.jpg",
						"large": "https://img3.doubanio.com\/view\/celebrity\/s_ratio_celebrity\/public\/p21430.jpg",
						"medium": "https://img3.doubanio.com\/view\/celebrity\/s_ratio_celebrity\/public\/p21430.jpg"
					},
					"name": "韩素媛",
					"id": "1178533"
				},
				{
					"alt": "https:\/\/movie.douban.com\/celebrity\/1364829\/",
					"avatars": {
						"small": "https://img1.doubanio.com\/view\/celebrity\/s_ratio_celebrity\/public\/p1527647410.08.jpg",
						"large": "https://img1.doubanio.com\/view\/celebrity\/s_ratio_celebrity\/public\/p1527647410.08.jpg",
						"medium": "https://img1.doubanio.com\/view\/celebrity\/s_ratio_celebrity\/public\/p1527647410.08.jpg"
					},
					"name": "蓝波",
					"id": "1364829"
				},
				{
					"alt": "https:\/\/movie.douban.com\/celebrity\/1394380\/",
					"avatars": {
						"small": "https://img3.doubanio.com\/view\/celebrity\/s_ratio_celebrity\/public\/p1527658154.64.jpg",
						"large": "https://img3.doubanio.com\/view\/celebrity\/s_ratio_celebrity\/public\/p1527658154.64.jpg",
						"medium": "https://img3.doubanio.com\/view\/celebrity\/s_ratio_celebrity\/public\/p1527658154.64.jpg"
					},
					"name": "庞贝童",
					"id": "1394380"
				}
			],
			"collect_count": 23,
			"original_title": "细思极恐",
			"subtype": "movie",
			"directors": [
				{
					"alt": "https:\/\/movie.douban.com\/celebrity\/1394332\/",
					"avatars": {
						"small": "https://img3.doubanio.com\/view\/celebrity\/s_ratio_celebrity\/public\/p1527746059.06.jpg",
						"large": "https://img3.doubanio.com\/view\/celebrity\/s_ratio_celebrity\/public\/p1527746059.06.jpg",
						"medium": "https://img3.doubanio.com\/view\/celebrity\/s_ratio_celebrity\/public\/p1527746059.06.jpg"
					},
					"name": "张跃斌",
					"id": "1394332"
				}
			],
			"year": "2018",
			"images": {
				"small": "https://img3.doubanio.com\/view\/photo\/s_ratio_poster\/public\/p2523632181.jpg",
				"large": "https://img3.doubanio.com\/view\/photo\/s_ratio_poster\/public\/p2523632181.jpg",
				"medium": "https://img3.doubanio.com\/view\/photo\/s_ratio_poster\/public\/p2523632181.jpg"
			},
			"alt": "https:\/\/movie.douban.com\/subject\/30235134\/",
			"id": "30235134"
		},
		{
			"rating": {
				"max": 10,
				"average": 8.0,
				"stars": "40",
				"min": 0
			},
			"genres": [
				"喜剧",
				"家庭"
			],
			"title": "生存家族",
			"casts": [
				{
					"alt": "https:\/\/movie.douban.com\/celebrity\/1009219\/",
					"avatars": {
						"small": "https://img3.doubanio.com\/view\/celebrity\/s_ratio_celebrity\/public\/p2131.jpg",
						"large": "https://img3.doubanio.com\/view\/celebrity\/s_ratio_celebrity\/public\/p2131.jpg",
						"medium": "https://img3.doubanio.com\/view\/celebrity\/s_ratio_celebrity\/public\/p2131.jpg"
					},
					"name": "小日向文世",
					"id": "1009219"
				},
				{
					"alt": "https:\/\/movie.douban.com\/celebrity\/1014844\/",
					"avatars": {
						"small": "https://img3.doubanio.com\/view\/celebrity\/s_ratio_celebrity\/public\/p16385.jpg",
						"large": "https://img3.doubanio.com\/view\/celebrity\/s_ratio_celebrity\/public\/p16385.jpg",
						"medium": "https://img3.doubanio.com\/view\/celebrity\/s_ratio_celebrity\/public\/p16385.jpg"
					},
					"name": "深津绘里",
					"id": "1014844"
				},
				{
					"alt": "https:\/\/movie.douban.com\/celebrity\/1315238\/",
					"avatars": {
						"small": "https://img3.doubanio.com\/view\/celebrity\/s_ratio_celebrity\/public\/p1506179491.3.jpg",
						"large": "https://img3.doubanio.com\/view\/celebrity\/s_ratio_celebrity\/public\/p1506179491.3.jpg",
						"medium": "https://img3.doubanio.com\/view\/celebrity\/s_ratio_celebrity\/public\/p1506179491.3.jpg"
					},
					"name": "泉泽祐希",
					"id": "1315238"
				}
			],
			"collect_count": 42463,
			"original_title": "サバイバルファミリー",
			"subtype": "movie",
			"directors": [
				{
					"alt": "https:\/\/movie.douban.com\/celebrity\/1164069\/",
					"avatars": {
						"small": "https://img1.doubanio.com\/view\/celebrity\/s_ratio_celebrity\/public\/p26869.jpg",
						"large": "https://img1.doubanio.com\/view\/celebrity\/s_ratio_celebrity\/public\/p26869.jpg",
						"medium": "https://img1.doubanio.com\/view\/celebrity\/s_ratio_celebrity\/public\/p26869.jpg"
					},
					"name": "矢口史靖",
					"id": "1164069"
				}
			],
			"year": "2017",
			"images": {
				"small": "https://img3.doubanio.com\/view\/photo\/s_ratio_poster\/public\/p2525716036.jpg",
				"large": "https://img3.doubanio.com\/view\/photo\/s_ratio_poster\/public\/p2525716036.jpg",
				"medium": "https://img3.doubanio.com\/view\/photo\/s_ratio_poster\/public\/p2525716036.jpg"
			},
			"alt": "https:\/\/movie.douban.com\/subject\/26815162\/",
			"id": "26815162"
		},
		{
			"rating": {
				"max": 10,
				"average": 5.1,
				"stars": "25",
				"min": 0
			},
			"genres": [
				"喜剧",
				"动作",
				"犯罪"
			],
			"title": "龙虾刑警",
			"casts": [
				{
					"alt": "https:\/\/movie.douban.com\/celebrity\/1314827\/",
					"avatars": {
						"small": "https://img1.doubanio.com\/view\/celebrity\/s_ratio_celebrity\/public\/p1445948736.67.jpg",
						"large": "https://img1.doubanio.com\/view\/celebrity\/s_ratio_celebrity\/public\/p1445948736.67.jpg",
						"medium": "https://img1.doubanio.com\/view\/celebrity\/s_ratio_celebrity\/public\/p1445948736.67.jpg"
					},
					"name": "王千源",
					"id": "1314827"
				},
				{
					"alt": "https:\/\/movie.douban.com\/celebrity\/1316067\/",
					"avatars": {
						"small": "https://img3.doubanio.com\/view\/celebrity\/s_ratio_celebrity\/public\/p1372668848.86.jpg",
						"large": "https://img3.doubanio.com\/view\/celebrity\/s_ratio_celebrity\/public\/p1372668848.86.jpg",
						"medium": "https://img3.doubanio.com\/view\/celebrity\/s_ratio_celebrity\/public\/p1372668848.86.jpg"
					},
					"name": "袁姗姗",
					"id": "1316067"
				},
				{
					"alt": "https:\/\/movie.douban.com\/celebrity\/1274276\/",
					"avatars": {
						"small": "https://img3.doubanio.com\/view\/celebrity\/s_ratio_celebrity\/public\/p1403277374.05.jpg",
						"large": "https://img3.doubanio.com\/view\/celebrity\/s_ratio_celebrity\/public\/p1403277374.05.jpg",
						"medium": "https://img3.doubanio.com\/view\/celebrity\/s_ratio_celebrity\/public\/p1403277374.05.jpg"
					},
					"name": "刘桦",
					"id": "1274276"
				}
			],
			"collect_count": 4844,
			"original_title": "龙虾刑警",
			"subtype": "movie",
			"directors": [
				{
					"alt": "https:\/\/movie.douban.com\/celebrity\/1312794\/",
					"avatars": {
						"small": "https://img1.doubanio.com\/view\/celebrity\/s_ratio_celebrity\/public\/p38549.jpg",
						"large": "https://img1.doubanio.com\/view\/celebrity\/s_ratio_celebrity\/public\/p38549.jpg",
						"medium": "https://img1.doubanio.com\/view\/celebrity\/s_ratio_celebrity\/public\/p38549.jpg"
					},
					"name": "李昕芸",
					"id": "1312794"
				}
			],
			"year": "2018",
			"images": {
				"small": "https://img3.doubanio.com\/view\/photo\/s_ratio_poster\/public\/p2523437806.jpg",
				"large": "https://img3.doubanio.com\/view\/photo\/s_ratio_poster\/public\/p2523437806.jpg",
				"medium": "https://img3.doubanio.com\/view\/photo\/s_ratio_poster\/public\/p2523437806.jpg"
			},
			"alt": "https:\/\/movie.douban.com\/subject\/26992383\/",
			"id": "26992383"
		},
		{
			"rating": {
				"max": 10,
				"average": 7.1,
				"stars": "35",
				"min": 0
			},
			"genres": [
				"剧情",
				"运动"
			],
			"title": "最后一球",
			"casts": [
				{
					"alt": "https:\/\/movie.douban.com\/celebrity\/1213388\/",
					"avatars": {
						"small": "https://img3.doubanio.com\/view\/celebrity\/s_ratio_celebrity\/public\/p1369731801.62.jpg",
						"large": "https://img3.doubanio.com\/view\/celebrity\/s_ratio_celebrity\/public\/p1369731801.62.jpg",
						"medium": "https://img3.doubanio.com\/view\/celebrity\/s_ratio_celebrity\/public\/p1369731801.62.jpg"
					},
					"name": "丹尼拉·科兹洛夫斯基",
					"id": "1213388"
				},
				{
					"alt": "https:\/\/movie.douban.com\/celebrity\/1327043\/",
					"avatars": {
						"small": "https://img1.doubanio.com\/view\/celebrity\/s_ratio_celebrity\/public\/pcVXPtI6sP8cel_avatar_uploaded1361267584.89.jpg",
						"large": "https://img1.doubanio.com\/view\/celebrity\/s_ratio_celebrity\/public\/pcVXPtI6sP8cel_avatar_uploaded1361267584.89.jpg",
						"medium": "https://img1.doubanio.com\/view\/celebrity\/s_ratio_celebrity\/public\/pcVXPtI6sP8cel_avatar_uploaded1361267584.89.jpg"
					},
					"name": "奥莉亚·祖耶娃",
					"id": "1327043"
				},
				{
					"alt": "https:\/\/movie.douban.com\/celebrity\/1394680\/",
					"avatars": {
						"small": "https://img1.doubanio.com\/f\/movie\/ca527386eb8c4e325611e22dfcb04cc116d6b423\/pics\/movie\/celebrity-default-small.png",
						"large": "https://img3.doubanio.com\/f\/movie\/63acc16ca6309ef191f0378faf793d1096a3e606\/pics\/movie\/celebrity-default-large.png",
						"medium": "https://img1.doubanio.com\/f\/movie\/8dd0c794499fe925ae2ae89ee30cd225750457b4\/pics\/movie\/celebrity-default-medium.png"
					},
					"name": "Vitaliy Andreev",
					"id": "1394680"
				}
			],
			"collect_count": 1282,
			"original_title": "Тренер",
			"subtype": "movie",
			"directors": [
				{
					"alt": "https:\/\/movie.douban.com\/celebrity\/1213388\/",
					"avatars": {
						"small": "https://img3.doubanio.com\/view\/celebrity\/s_ratio_celebrity\/public\/p1369731801.62.jpg",
						"large": "https://img3.doubanio.com\/view\/celebrity\/s_ratio_celebrity\/public\/p1369731801.62.jpg",
						"medium": "https://img3.doubanio.com\/view\/celebrity\/s_ratio_celebrity\/public\/p1369731801.62.jpg"
					},
					"name": "丹尼拉·科兹洛夫斯基",
					"id": "1213388"
				}
			],
			"year": "2018",
			"images": {
				"small": "https://img3.doubanio.com\/view\/photo\/s_ratio_poster\/public\/p2526211692.jpg",
				"large": "https://img3.doubanio.com\/view\/photo\/s_ratio_poster\/public\/p2526211692.jpg",
				"medium": "https://img3.doubanio.com\/view\/photo\/s_ratio_poster\/public\/p2526211692.jpg"
			},
			"alt": "https:\/\/movie.douban.com\/subject\/27202825\/",
			"id": "27202825"
		},
		{
			"rating": {
				"max": 10,
				"average": 8.2,
				"stars": "45",
				"min": 0
			},
			"genres": [
				"动作",
				"科幻",
				"奇幻"
			],
			"title": "复仇者联盟3：无限战争",
			"casts": [
				{
					"alt": "https:\/\/movie.douban.com\/celebrity\/1016681\/",
					"avatars": {
						"small": "https://img1.doubanio.com\/view\/celebrity\/s_ratio_celebrity\/public\/p56339.jpg",
						"large": "https://img1.doubanio.com\/view\/celebrity\/s_ratio_celebrity\/public\/p56339.jpg",
						"medium": "https://img1.doubanio.com\/view\/celebrity\/s_ratio_celebrity\/public\/p56339.jpg"
					},
					"name": "小罗伯特·唐尼",
					"id": "1016681"
				},
				{
					"alt": "https:\/\/movie.douban.com\/celebrity\/1021959\/",
					"avatars": {
						"small": "https://img3.doubanio.com\/view\/celebrity\/s_ratio_celebrity\/public\/p4053.jpg",
						"large": "https://img3.doubanio.com\/view\/celebrity\/s_ratio_celebrity\/public\/p4053.jpg",
						"medium": "https://img3.doubanio.com\/view\/celebrity\/s_ratio_celebrity\/public\/p4053.jpg"
					},
					"name": "克里斯·海姆斯沃斯",
					"id": "1021959"
				},
				{
					"alt": "https:\/\/movie.douban.com\/celebrity\/1017885\/",
					"avatars": {
						"small": "https://img1.doubanio.com\/view\/celebrity\/s_ratio_celebrity\/public\/p1359877729.49.jpg",
						"large": "https://img1.doubanio.com\/view\/celebrity\/s_ratio_celebrity\/public\/p1359877729.49.jpg",
						"medium": "https://img1.doubanio.com\/view\/celebrity\/s_ratio_celebrity\/public\/p1359877729.49.jpg"
					},
					"name": "克里斯·埃文斯",
					"id": "1017885"
				}
			],
			"collect_count": 347477,
			"original_title": "Avengers: Infinity War",
			"subtype": "movie",
			"directors": [
				{
					"alt": "https:\/\/movie.douban.com\/celebrity\/1321812\/",
					"avatars": {
						"small": "https://img3.doubanio.com\/view\/celebrity\/s_ratio_celebrity\/public\/p51466.jpg",
						"large": "https://img3.doubanio.com\/view\/celebrity\/s_ratio_celebrity\/public\/p51466.jpg",
						"medium": "https://img3.doubanio.com\/view\/celebrity\/s_ratio_celebrity\/public\/p51466.jpg"
					},
					"name": "安东尼·罗素",
					"id": "1321812"
				},
				{
					"alt": "https:\/\/movie.douban.com\/celebrity\/1320870\/",
					"avatars": {
						"small": "https://img1.doubanio.com\/view\/celebrity\/s_ratio_celebrity\/public\/p1525505053.79.jpg",
						"large": "https://img1.doubanio.com\/view\/celebrity\/s_ratio_celebrity\/public\/p1525505053.79.jpg",
						"medium": "https://img1.doubanio.com\/view\/celebrity\/s_ratio_celebrity\/public\/p1525505053.79.jpg"
					},
					"name": "乔·罗素",
					"id": "1320870"
				}
			],
			"year": "2018",
			"images": {
				"small": "https://img3.doubanio.com\/view\/photo\/s_ratio_poster\/public\/p2517753454.jpg",
				"large": "https://img3.doubanio.com\/view\/photo\/s_ratio_poster\/public\/p2517753454.jpg",
				"medium": "https://img3.doubanio.com\/view\/photo\/s_ratio_poster\/public\/p2517753454.jpg"
			},
			"alt": "https:\/\/movie.douban.com\/subject\/24773958\/",
			"id": "24773958"
		},
		{
			"rating": {
				"max": 10,
				"average": 7.1,
				"stars": "35",
				"min": 0
			},
			"genres": [
				"喜剧",
				"奇幻"
			],
			"title": "超时空同居",
			"casts": [
				{
					"alt": "https:\/\/movie.douban.com\/celebrity\/1312940\/",
					"avatars": {
						"small": "https://img3.doubanio.com\/view\/celebrity\/s_ratio_celebrity\/public\/p1503986232.61.jpg",
						"large": "https://img3.doubanio.com\/view\/celebrity\/s_ratio_celebrity\/public\/p1503986232.61.jpg",
						"medium": "https://img3.doubanio.com\/view\/celebrity\/s_ratio_celebrity\/public\/p1503986232.61.jpg"
					},
					"name": "雷佳音",
					"id": "1312940"
				},
				{
					"alt": "https:\/\/movie.douban.com\/celebrity\/1275756\/",
					"avatars": {
						"small": "https://img3.doubanio.com\/view\/celebrity\/s_ratio_celebrity\/public\/p1367210981.95.jpg",
						"large": "https://img3.doubanio.com\/view\/celebrity\/s_ratio_celebrity\/public\/p1367210981.95.jpg",
						"medium": "https://img3.doubanio.com\/view\/celebrity\/s_ratio_celebrity\/public\/p1367210981.95.jpg"
					},
					"name": "佟丽娅",
					"id": "1275756"
				},
				{
					"alt": "https:\/\/movie.douban.com\/celebrity\/1325751\/",
					"avatars": {
						"small": "https://img1.doubanio.com\/view\/celebrity\/s_ratio_celebrity\/public\/p1499435823.67.jpg",
						"large": "https://img1.doubanio.com\/view\/celebrity\/s_ratio_celebrity\/public\/p1499435823.67.jpg",
						"medium": "https://img1.doubanio.com\/view\/celebrity\/s_ratio_celebrity\/public\/p1499435823.67.jpg"
					},
					"name": "张衣",
					"id": "1325751"
				}
			],
			"collect_count": 150949,
			"original_title": "超时空同居",
			"subtype": "movie",
			"directors": [
				{
					"alt": "https:\/\/movie.douban.com\/celebrity\/1331887\/",
					"avatars": {
						"small": "https://img3.doubanio.com\/view\/celebrity\/s_ratio_celebrity\/public\/p1520837465.56.jpg",
						"large": "https://img3.doubanio.com\/view\/celebrity\/s_ratio_celebrity\/public\/p1520837465.56.jpg",
						"medium": "https://img3.doubanio.com\/view\/celebrity\/s_ratio_celebrity\/public\/p1520837465.56.jpg"
					},
					"name": "苏伦",
					"id": "1331887"
				}
			],
			"year": "2018",
			"images": {
				"small": "https://img1.doubanio.com\/view\/photo\/s_ratio_poster\/public\/p2520331478.jpg",
				"large": "https://img1.doubanio.com\/view\/photo\/s_ratio_poster\/public\/p2520331478.jpg",
				"medium": "https://img1.doubanio.com\/view\/photo\/s_ratio_poster\/public\/p2520331478.jpg"
			},
			"alt": "https:\/\/movie.douban.com\/subject\/27133303\/",
			"id": "27133303"
		},
		{
			"rating": {
				"max": 10,
				"average": 6.8,
				"stars": "35",
				"min": 0
			},
			"genres": [
				"动作",
				"动画",
				"奇幻"
			],
			"title": "暹罗决：九神战甲",
			"casts": [
				{
					"alt": "https:\/\/movie.douban.com\/celebrity\/1394650\/",
					"avatars": {
						"small": "https://img1.doubanio.com\/f\/movie\/ca527386eb8c4e325611e22dfcb04cc116d6b423\/pics\/movie\/celebrity-default-small.png",
						"large": "https://img3.doubanio.com\/f\/movie\/63acc16ca6309ef191f0378faf793d1096a3e606\/pics\/movie\/celebrity-default-large.png",
						"medium": "https://img1.doubanio.com\/f\/movie\/8dd0c794499fe925ae2ae89ee30cd225750457b4\/pics\/movie\/celebrity-default-medium.png"
					},
					"name": "卡诺查·曼雅德昂",
					"id": "1394650"
				},
				{
					"alt": "https:\/\/movie.douban.com\/celebrity\/1394651\/",
					"avatars": {
						"small": "https://img1.doubanio.com\/f\/movie\/ca527386eb8c4e325611e22dfcb04cc116d6b423\/pics\/movie\/celebrity-default-small.png",
						"large": "https://img3.doubanio.com\/f\/movie\/63acc16ca6309ef191f0378faf793d1096a3e606\/pics\/movie\/celebrity-default-large.png",
						"medium": "https://img1.doubanio.com\/f\/movie\/8dd0c794499fe925ae2ae89ee30cd225750457b4\/pics\/movie\/celebrity-default-medium.png"
					},
					"name": "萨维提·苏提查农",
					"id": "1394651"
				},
				{
					"alt": "https:\/\/movie.douban.com\/celebrity\/1394652\/",
					"avatars": {
						"small": "https://img1.doubanio.com\/f\/movie\/ca527386eb8c4e325611e22dfcb04cc116d6b423\/pics\/movie\/celebrity-default-small.png",
						"large": "https://img3.doubanio.com\/f\/movie\/63acc16ca6309ef191f0378faf793d1096a3e606\/pics\/movie\/celebrity-default-large.png",
						"medium": "https://img1.doubanio.com\/f\/movie\/8dd0c794499fe925ae2ae89ee30cd225750457b4\/pics\/movie\/celebrity-default-medium.png"
					},
					"name": "Sirichai Charoenkijtanakul",
					"id": "1394652"
				}
			],
			"collect_count": 1035,
			"original_title": "The Legend of Muay Thai: 9 Satra",
			"subtype": "movie",
			"directors": [
				{
					"alt": "https:\/\/movie.douban.com\/celebrity\/1394664\/",
					"avatars": {
						"small": "https://img1.doubanio.com\/f\/movie\/ca527386eb8c4e325611e22dfcb04cc116d6b423\/pics\/movie\/celebrity-default-small.png",
						"large": "https://img3.doubanio.com\/f\/movie\/63acc16ca6309ef191f0378faf793d1096a3e606\/pics\/movie\/celebrity-default-large.png",
						"medium": "https://img1.doubanio.com\/f\/movie\/8dd0c794499fe925ae2ae89ee30cd225750457b4\/pics\/movie\/celebrity-default-medium.png"
					},
					"name": "彭萨·康斯里",
					"id": "1394664"
				},
				{
					"alt": "https:\/\/movie.douban.com\/celebrity\/1394665\/",
					"avatars": {
						"small": "https://img1.doubanio.com\/f\/movie\/ca527386eb8c4e325611e22dfcb04cc116d6b423\/pics\/movie\/celebrity-default-small.png",
						"large": "https://img3.doubanio.com\/f\/movie\/63acc16ca6309ef191f0378faf793d1096a3e606\/pics\/movie\/celebrity-default-large.png",
						"medium": "https://img1.doubanio.com\/f\/movie\/8dd0c794499fe925ae2ae89ee30cd225750457b4\/pics\/movie\/celebrity-default-medium.png"
					},
					"name": "甘·方苏旺",
					"id": "1394665"
				}
			],
			"year": "2018",
			"images": {
				"small": "https://img3.doubanio.com\/view\/photo\/s_ratio_poster\/public\/p2524042454.jpg",
				"large": "https://img3.doubanio.com\/view\/photo\/s_ratio_poster\/public\/p2524042454.jpg",
				"medium": "https://img3.doubanio.com\/view\/photo\/s_ratio_poster\/public\/p2524042454.jpg"
			},
			"alt": "https:\/\/movie.douban.com\/subject\/27667334\/",
			"id": "27667334"
		},
		{
			"rating": {
				"max": 10,
				"average": 3.8,
				"stars": "20",
				"min": 0
			},
			"genres": [
				"喜剧"
			],
			"title": "幸福马上来",
			"casts": [
				{
					"alt": "https:\/\/movie.douban.com\/celebrity\/1274535\/",
					"avatars": {
						"small": "https://img3.doubanio.com\/view\/celebrity\/s_ratio_celebrity\/public\/p4973.jpg",
						"large": "https://img3.doubanio.com\/view\/celebrity\/s_ratio_celebrity\/public\/p4973.jpg",
						"medium": "https://img3.doubanio.com\/view\/celebrity\/s_ratio_celebrity\/public\/p4973.jpg"
					},
					"name": "冯巩",
					"id": "1274535"
				},
				{
					"alt": "https:\/\/movie.douban.com\/celebrity\/1315624\/",
					"avatars": {
						"small": "https://img3.doubanio.com\/view\/celebrity\/s_ratio_celebrity\/public\/p32820.jpg",
						"large": "https://img3.doubanio.com\/view\/celebrity\/s_ratio_celebrity\/public\/p32820.jpg",
						"medium": "https://img3.doubanio.com\/view\/celebrity\/s_ratio_celebrity\/public\/p32820.jpg"
					},
					"name": "毛俊杰",
					"id": "1315624"
				},
				{
					"alt": "https:\/\/movie.douban.com\/celebrity\/1336305\/",
					"avatars": {
						"small": "https://img3.doubanio.com\/view\/celebrity\/s_ratio_celebrity\/public\/p1473508881.63.jpg",
						"large": "https://img3.doubanio.com\/view\/celebrity\/s_ratio_celebrity\/public\/p1473508881.63.jpg",
						"medium": "https://img3.doubanio.com\/view\/celebrity\/s_ratio_celebrity\/public\/p1473508881.63.jpg"
					},
					"name": "刘昊然",
					"id": "1336305"
				}
			],
			"collect_count": 3778,
			"original_title": "幸福马上来",
			"subtype": "movie",
			"directors": [
				{
					"alt": "https:\/\/movie.douban.com\/celebrity\/1274535\/",
					"avatars": {
						"small": "https://img3.doubanio.com\/view\/celebrity\/s_ratio_celebrity\/public\/p4973.jpg",
						"large": "https://img3.doubanio.com\/view\/celebrity\/s_ratio_celebrity\/public\/p4973.jpg",
						"medium": "https://img3.doubanio.com\/view\/celebrity\/s_ratio_celebrity\/public\/p4973.jpg"
					},
					"name": "冯巩",
					"id": "1274535"
				},
				{
					"alt": "https:\/\/movie.douban.com\/celebrity\/1355104\/",
					"avatars": {
						"small": "https://img3.doubanio.com\/view\/celebrity\/s_ratio_celebrity\/public\/p1499080610.06.jpg",
						"large": "https://img3.doubanio.com\/view\/celebrity\/s_ratio_celebrity\/public\/p1499080610.06.jpg",
						"medium": "https://img3.doubanio.com\/view\/celebrity\/s_ratio_celebrity\/public\/p1499080610.06.jpg"
					},
					"name": "崔俊杰",
					"id": "1355104"
				}
			],
			"year": "2018",
			"images": {
				"small": "https://img1.doubanio.com\/view\/photo\/s_ratio_poster\/public\/p2521514148.jpg",
				"large": "https://img1.doubanio.com\/view\/photo\/s_ratio_poster\/public\/p2521514148.jpg",
				"medium": "https://img1.doubanio.com\/view\/photo\/s_ratio_poster\/public\/p2521514148.jpg"
			},
			"alt": "https:\/\/movie.douban.com\/subject\/26813286\/",
			"id": "26813286"
		},
		{
			"rating": {
				"max": 10,
				"average": 0,
				"stars": "00",
				"min": 0
			},
			"genres": [
				"喜剧",
				"动画",
				"冒险"
			],
			"title": "第七个小矮人",
			"casts": [
				{
					"alt": "https:\/\/movie.douban.com\/celebrity\/1010447\/",
					"avatars": {
						"small": "https://img1.doubanio.com\/f\/movie\/ca527386eb8c4e325611e22dfcb04cc116d6b423\/pics\/movie\/celebrity-default-small.png",
						"large": "https://img3.doubanio.com\/f\/movie\/63acc16ca6309ef191f0378faf793d1096a3e606\/pics\/movie\/celebrity-default-large.png",
						"medium": "https://img1.doubanio.com\/f\/movie\/8dd0c794499fe925ae2ae89ee30cd225750457b4\/pics\/movie\/celebrity-default-medium.png"
					},
					"name": "Otto Waalkes",
					"id": "1010447"
				},
				{
					"alt": "https:\/\/movie.douban.com\/celebrity\/1127409\/",
					"avatars": {
						"small": "https://img1.doubanio.com\/f\/movie\/ca527386eb8c4e325611e22dfcb04cc116d6b423\/pics\/movie\/celebrity-default-small.png",
						"large": "https://img3.doubanio.com\/f\/movie\/63acc16ca6309ef191f0378faf793d1096a3e606\/pics\/movie\/celebrity-default-large.png",
						"medium": "https://img1.doubanio.com\/f\/movie\/8dd0c794499fe925ae2ae89ee30cd225750457b4\/pics\/movie\/celebrity-default-medium.png"
					},
					"name": "Mirco Nontschew",
					"id": "1127409"
				},
				{
					"alt": "https:\/\/movie.douban.com\/celebrity\/1059956\/",
					"avatars": {
						"small": "https://img3.doubanio.com\/view\/celebrity\/s_ratio_celebrity\/public\/p1529933649.41.jpg",
						"large": "https://img3.doubanio.com\/view\/celebrity\/s_ratio_celebrity\/public\/p1529933649.41.jpg",
						"medium": "https://img3.doubanio.com\/view\/celebrity\/s_ratio_celebrity\/public\/p1529933649.41.jpg"
					},
					"name": "Boris Aljinovic",
					"id": "1059956"
				}
			],
			"collect_count": 564,
			"original_title": "The 7th Dwarf",
			"subtype": "movie",
			"directors": [
				{
					"alt": "https:\/\/movie.douban.com\/celebrity\/1059956\/",
					"avatars": {
						"small": "https://img3.doubanio.com\/view\/celebrity\/s_ratio_celebrity\/public\/p1529933649.41.jpg",
						"large": "https://img3.doubanio.com\/view\/celebrity\/s_ratio_celebrity\/public\/p1529933649.41.jpg",
						"medium": "https://img3.doubanio.com\/view\/celebrity\/s_ratio_celebrity\/public\/p1529933649.41.jpg"
					},
					"name": "Boris Aljinovic",
					"id": "1059956"
				},
				{
					"alt": "https:\/\/movie.douban.com\/celebrity\/1393195\/",
					"avatars": {
						"small": "https://img3.doubanio.com\/view\/celebrity\/s_ratio_celebrity\/public\/p1529156715.84.jpg",
						"large": "https://img3.doubanio.com\/view\/celebrity\/s_ratio_celebrity\/public\/p1529156715.84.jpg",
						"medium": "https://img3.doubanio.com\/view\/celebrity\/s_ratio_celebrity\/public\/p1529156715.84.jpg"
					},
					"name": "哈莱德·西博门",
					"id": "1393195"
				}
			],
			"year": "2014",
			"images": {
				"small": "https://img1.doubanio.com\/view\/photo\/s_ratio_poster\/public\/p2522252598.jpg",
				"large": "https://img1.doubanio.com\/view\/photo\/s_ratio_poster\/public\/p2522252598.jpg",
				"medium": "https://img1.doubanio.com\/view\/photo\/s_ratio_poster\/public\/p2522252598.jpg"
			},
			"alt": "https:\/\/movie.douban.com\/subject\/25971649\/",
			"id": "25971649"
		},
		{
			"rating": {
				"max": 10,
				"average": 0,
				"stars": "00",
				"min": 0
			},
			"genres": [
				"剧情",
				"犯罪",
				"悬疑"
			],
			"title": "只能活一个",
			"casts": [
				{
					"alt": "https:\/\/movie.douban.com\/celebrity\/1002998\/",
					"avatars": {
						"small": "https://img3.doubanio.com\/view\/celebrity\/s_ratio_celebrity\/public\/p20374.jpg",
						"large": "https://img3.doubanio.com\/view\/celebrity\/s_ratio_celebrity\/public\/p20374.jpg",
						"medium": "https://img3.doubanio.com\/view\/celebrity\/s_ratio_celebrity\/public\/p20374.jpg"
					},
					"name": "张峻宁",
					"id": "1002998"
				},
				{
					"alt": "https:\/\/movie.douban.com\/celebrity\/1356410\/",
					"avatars": {
						"small": "https://img1.doubanio.com\/view\/celebrity\/s_ratio_celebrity\/public\/p1495272189.28.jpg",
						"large": "https://img1.doubanio.com\/view\/celebrity\/s_ratio_celebrity\/public\/p1495272189.28.jpg",
						"medium": "https://img1.doubanio.com\/view\/celebrity\/s_ratio_celebrity\/public\/p1495272189.28.jpg"
					},
					"name": "石雨晴",
					"id": "1356410"
				},
				{
					"alt": "https:\/\/movie.douban.com\/celebrity\/1275965\/",
					"avatars": {
						"small": "https://img3.doubanio.com\/view\/celebrity\/s_ratio_celebrity\/public\/p1500536910.66.jpg",
						"large": "https://img3.doubanio.com\/view\/celebrity\/s_ratio_celebrity\/public\/p1500536910.66.jpg",
						"medium": "https://img3.doubanio.com\/view\/celebrity\/s_ratio_celebrity\/public\/p1500536910.66.jpg"
					},
					"name": "杜奕衡",
					"id": "1275965"
				}
			],
			"collect_count": 23,
			"original_title": "只能活一个",
			"subtype": "movie",
			"directors": [
				{
					"alt": "https:\/\/movie.douban.com\/celebrity\/1394054\/",
					"avatars": {
						"small": "https://img1.doubanio.com\/f\/movie\/ca527386eb8c4e325611e22dfcb04cc116d6b423\/pics\/movie\/celebrity-default-small.png",
						"large": "https://img3.doubanio.com\/f\/movie\/63acc16ca6309ef191f0378faf793d1096a3e606\/pics\/movie\/celebrity-default-large.png",
						"medium": "https://img1.doubanio.com\/f\/movie\/8dd0c794499fe925ae2ae89ee30cd225750457b4\/pics\/movie\/celebrity-default-medium.png"
					},
					"name": "孙杰",
					"id": "1394054"
				}
			],
			"year": "2018",
			"images": {
				"small": "https://img1.doubanio.com\/view\/photo\/s_ratio_poster\/public\/p2524300287.jpg",
				"large": "https://img1.doubanio.com\/view\/photo\/s_ratio_poster\/public\/p2524300287.jpg",
				"medium": "https://img1.doubanio.com\/view\/photo\/s_ratio_poster\/public\/p2524300287.jpg"
			},
			"alt": "https:\/\/movie.douban.com\/subject\/27195126\/",
			"id": "27195126"
		},
		{
			"rating": {
				"max": 10,
				"average": 6.4,
				"stars": "35",
				"min": 0
			},
			"genres": [
				"剧情",
				"传记",
				"历史"
			],
			"title": "青年马克思",
			"casts": [
				{
					"alt": "https:\/\/movie.douban.com\/celebrity\/1014063\/",
					"avatars": {
						"small": "https://img3.doubanio.com\/view\/celebrity\/s_ratio_celebrity\/public\/p22970.jpg",
						"large": "https://img3.doubanio.com\/view\/celebrity\/s_ratio_celebrity\/public\/p22970.jpg",
						"medium": "https://img3.doubanio.com\/view\/celebrity\/s_ratio_celebrity\/public\/p22970.jpg"
					},
					"name": "奥古斯特·迪尔",
					"id": "1014063"
				},
				{
					"alt": "https:\/\/movie.douban.com\/celebrity\/1387917\/",
					"avatars": {
						"small": "https://img3.doubanio.com\/view\/celebrity\/s_ratio_celebrity\/public\/p1517306102.13.jpg",
						"large": "https://img3.doubanio.com\/view\/celebrity\/s_ratio_celebrity\/public\/p1517306102.13.jpg",
						"medium": "https://img3.doubanio.com\/view\/celebrity\/s_ratio_celebrity\/public\/p1517306102.13.jpg"
					},
					"name": "史特凡·柯纳斯克",
					"id": "1387917"
				},
				{
					"alt": "https:\/\/movie.douban.com\/celebrity\/1341743\/",
					"avatars": {
						"small": "https://img3.doubanio.com\/view\/celebrity\/s_ratio_celebrity\/public\/p1406537335.62.jpg",
						"large": "https://img3.doubanio.com\/view\/celebrity\/s_ratio_celebrity\/public\/p1406537335.62.jpg",
						"medium": "https://img3.doubanio.com\/view\/celebrity\/s_ratio_celebrity\/public\/p1406537335.62.jpg"
					},
					"name": "薇姬·克里普斯",
					"id": "1341743"
				}
			],
			"collect_count": 4191,
			"original_title": "Le jeune Karl Marx",
			"subtype": "movie",
			"directors": [
				{
					"alt": "https:\/\/movie.douban.com\/celebrity\/1294186\/",
					"avatars": {
						"small": "https://img1.doubanio.com\/view\/celebrity\/s_ratio_celebrity\/public\/p1484919465.79.jpg",
						"large": "https://img1.doubanio.com\/view\/celebrity\/s_ratio_celebrity\/public\/p1484919465.79.jpg",
						"medium": "https://img1.doubanio.com\/view\/celebrity\/s_ratio_celebrity\/public\/p1484919465.79.jpg"
					},
					"name": "哈乌·佩克",
					"id": "1294186"
				}
			],
			"year": "2017",
			"images": {
				"small": "https://img3.doubanio.com\/view\/photo\/s_ratio_poster\/public\/p2521271645.jpg",
				"large": "https://img3.doubanio.com\/view\/photo\/s_ratio_poster\/public\/p2521271645.jpg",
				"medium": "https://img3.doubanio.com\/view\/photo\/s_ratio_poster\/public\/p2521271645.jpg"
			},
			"alt": "https:\/\/movie.douban.com\/subject\/5330387\/",
			"id": "5330387"
		}
	],
	"title": "正在上映的电影-北京"
}